credit/VERSION
credit/__init__.py
credit/animation.py
credit/boundary_padding.py
credit/data.py
credit/data404.py
credit/distributed.py
credit/forecast.py
credit/interp.py
credit/loss.py
credit/loss404.py
credit/metrics.py
credit/mixed_precision.py
credit/nwp.py
credit/output.py
credit/parser.py
credit/pbs.py
credit/physics_constants.py
credit/physics_core.py
credit/pol_lapdiff_filt.py
credit/postblock.py
credit/regrid.py
credit/replay_buffer.py
credit/scheduler.py
credit/seed.py
credit/skebs.py
credit/solar.py
credit/transforms.py
credit/transforms404.py
credit/visualization_tools.py
credit/xr_sampler.py
credit/datasets/__init__.py
credit/datasets/era5_multistep.py
credit/datasets/era5_multistep_batcher.py
credit/datasets/era5_singlestep.py
credit/datasets/load_dataset_and_dataloader.py
credit/datasets/realtime_predict.py
credit/datasets/sequential_multistep.py
credit/ensemble/__init__.py
credit/ensemble/bred_vector.py
credit/ensemble/crps.py
credit/ensemble/gaussian_noise.py
credit/metadata/CESM_Lev_Info.nc
credit/metadata/ERA5_Lev_Info.nc
credit/metadata/L137_model_level_indices.csv
credit/metadata/__init__.py
credit/metadata/era5.yaml
credit/metadata/era5_old.yaml
credit/models/__init__.py
credit/models/base_model.py
credit/models/checkpoint.py
credit/models/crossformer.py
credit/models/crossformer_diffusion.py
credit/models/crossformer_ensemble.py
credit/models/debugger_model.py
credit/models/fuxi.py
credit/models/graph.py
credit/models/reset.py
credit/models/swin.py
credit/models/unet.py
credit/models/unet404.py
credit/trainers/__init__.py
credit/trainers/base_trainer.py
credit/trainers/trainer404.py
credit/trainers/trainerERA5.py
credit/trainers/trainerERA5_ensemble.py
credit/trainers/utils.py
credit/trainers/deprecated/trainerERA5_multistep_concat.py
credit/trainers/deprecated/trainerERA5_multistep_sum.py
credit/trainers/deprecated/trainerERA5_multistep_v1.py
credit/trainers/deprecated/trainerERA5_v1.py
credit/trainers/deprecated/trainerERA5_v2.py
miles_credit-2025.2.0.dist-info/licenses/LICENSE
miles_credit-2025.2.0.dist-info/METADATA
miles_credit-2025.2.0.dist-info/WHEEL
miles_credit-2025.2.0.dist-info/top_level.txt
miles_credit-2025.2.0.dist-info/RECORD
