Metadata-Version: 2.4
Name: miles-credit
Version: 2025.2.0
Author-email: "NCAR Machine Integration and Learning for Earth Systems (MILES)" <miles@ucar.edu>
License:                                  Apache License
Requires-Python: >=3.8
License-File: LICENSE
Requires-Dist: numpy
Requires-Dist: pandas
Requires-Dist: matplotlib
Requires-Dist: cartopy
Requires-Dist: scikit-learn
Requires-Dist: pyarrow
Requires-Dist: pytest
Requires-Dist: xarray
Requires-Dist: netcdf4
Requires-Dist: torch
Requires-Dist: torchvision
Requires-Dist: pyyaml
Requires-Dist: cartopy
Requires-Dist: dask
Requires-Dist: distributed
Requires-Dist: dask-jobqueue
Requires-Dist: zarr
Requires-Dist: einops
Requires-Dist: echo-opt
Requires-Dist: bridgescaler
Requires-Dist: segmentation-models-pytorch
Requires-Dist: haversine
Requires-Dist: pvlib
Requires-Dist: torch-harmonics
Requires-Dist: torch_geometric
Requires-Dist: pre-commit
Requires-Dist: ruff
Requires-Dist: sphinx
Requires-Dist: sphinx-autoapi
Requires-Dist: myst_parser
Requires-Dist: sphinx-book-theme
Requires-Dist: fsspec
Requires-Dist: gcsfs
Dynamic: license-file
